cpt_module/__init__.py
cpt_module/cpt_module.py
cpt_module/libcpt_module.so
cpt_module-1.0.3.dist-info/METADATA
cpt_module-1.0.3.dist-info/WHEEL
cpt_module-1.0.3.dist-info/top_level.txt
cpt_module-1.0.3.dist-info/RECORD
