Metadata-Version: 2.1
Name: cpt_module
Version: 1.0.3
Summary: A Python module wrapping a Rust shared library for encryption and decryption - CPT
